renovation_ad/__init__.py
renovation_ad/core.py
renovation_ad/engines.py
renovation_ad/utils.py
renovation_ad-0.1.1.dist-info/LICENSE
renovation_ad-0.1.1.dist-info/METADATA
renovation_ad-0.1.1.dist-info/WHEEL
renovation_ad-0.1.1.dist-info/top_level.txt
renovation_ad-0.1.1.dist-info/RECORD
