Metadata-Version: 2.1
Name: renovation-ad
Version: 0.1.1
Summary: A high-performance HTML ad cleaner using Adblock rules (Pure Python + lxml).
Home-page: https://github.com/yourusername/renovation-ad
Author: h-o-w-a-r-d(Iced_cocktails)
Author-email: howard-11-26@proton.me
License: UNKNOWN
Platform: UNKNOWN
Classifier: Programming Language :: Python :: 3
Classifier: License :: OSI Approved :: MIT License
Classifier: Operating System :: OS Independent
Classifier: Topic :: Internet :: WWW/HTTP
Classifier: Topic :: Text Processing :: Markup :: HTML
Requires-Python: >=3.7
License-File: LICENSE
Requires-Dist: requests (>=2.25.0)
Requires-Dist: lxml (>=4.6.0)
Requires-Dist: cssselect (>=1.1.0)
Requires-Dist: beautifulsoup4 (>=4.9.0)
